{
	"": "",
	"10/Sheet": "10/Sheet",
	"2/Sheet": "2/Sheet",
	"A": "A",
	"About": "About",
	"AboveOrBelowBenchmark": "Above or Below Benchmark",
	"AbsoluteAmountDifference": "Absolute Cost Difference",
	"AbsoluteQuantityDifference": "Absolute Quantity Difference",
	"AccountPayments": "Konto Betalinger",
	"AccountingDate": "Accounting Date",
	"AccountsReceivable": "Debitor",
	"AcquisitionCode": "Acquisition Code",
	"AcquisitionCodeValidationMessageForWarehouseTypeP": "Acquisition Code {0} is not allowed when copy to warehouse type is 'P'",
	"AcquisitionCodeValidationMessageForWarehouseTypeS": "Acquisition Code {0} is not allowed when copy to warehouse type is 'S'",
	"AcquisitionCost": "Acquisition Cost",
	"ActionDate": "handling Dato",
	"ActionStatus": "status",
	"Add": "Tilføje",
	"AddAllTagsToCount": "Add All Tags To Count",
	"AddNewDistributionOrder": "Add New Distribution Order",
	"AddNewPurchaseOrder": "Add New Purchase Order",
	"AddNewTag": "Add New Tag",
	"AddTagsToCount": "Add Tag(s) To Count",
	"Address": "Adresse",
	"Aging": "Aldrende",
	"AgingAndTotals": "Aldring & totaler",
	"AgingDataType": "Aging Datatype",
	"AgreedQuantity": "Agreed Quantity",
	"AgreementNumber": "Agreement Number",
	"AgreementType": "Agreement Type",
	"AllInvoices": "All Invoices",
	"AllocatableNetQuantity": "Allocatable Net Quantity",
	"AllocatableQuantity": "Allocatable Quantity",
	"AllocatedQuantity": "Allocated Quantity",
	"AllocationMethod": "Allocation Method",
	"AlternateItem": "Alternate Item",
	"AlternateQuantity": "Alternativ Mængde",
	"AlternateU/M": "Alternate Unit of Measure",
	"AlternateUM": "Alternativ Unit",
	"AmountSentToCollections": "Beløb Sendt til samlinger",
	"AnnualReviewDate": "Annual Review Dato",
	"AnnualSales": "Annual Sales",
	"AutomaticTranslations": "Automatic Translations",
	"AutomaticTranslationsHelpText": "These were generated automatically and may contain incorrect translations. If translations in your language are missing or incorrect, please contact LeanSwift and help us make them right.",
	"AvailableNetQuantity": "Available Net Quantity",
	"AverageCost": "Average Cost",
	"AverageDaysToPay": "Gennemsnitlige dage til at betale",
	"AverageMonthly": "Average Monthly",
	"B": "B",
	"Back": "Back",
	"Balance": "Balance",
	"BalanceIdentity": "Balance Identity",
	"BalancesHighPeriod": "Saldi / Høj Periode",
	"BankAccountID": "Bankkonto ID",
	"BarcodeLabels": "Barcode Labels",
	"BarcodeType": "Barcode Type",
	"BaseConversionFactor": "Base Conversion Factor",
	"BaseQuantity": "Base Quantity",
	"BasicData": "basisdata",
	"BasicUnitOfMeasure": "Grundlæggende måleenhed",
	"BatchNo": "batch Number",
	"BinLabels": "Bin Labels",
	"BinLocation": "Bin Location",
	"BuildersHoldQuantity": "Builders Hold Quantity",
	"C": "C",
	"CODemand": "CO Demand",
	"CODemandAllocated": "CO Demand Allocated",
	"CODemandNotAllocatedWithinTimeFence": "CO Demand Not Allocated Within Time Fence",
	"CalculationFactor": "Beregning Factor",
	"Cancel": "Ophæve",
	"CardNo": "Kort nummer",
	"CardType": "korttype",
	"CashDiscAmount": "Rabat Beløb",
	"CashDiscountDate": "Discount Dato",
	"CashPaymentDetails": "Kontant Betalingsoplysninger",
	"CashPayments": "Udbetalinger",
	"ChangedByUser": "Changed By User",
	"Charge": "Oplade",
	"Charges": "Afgifter",
	"CheckNo": "Tjek Number",
	"Clear": "Klar",
	"Clearance": "Clearance",
	"CoNumberMandatoryABBR": "CO Mandatory",
	"Code128(1D)": "Code 128(1D)",
	"CollectionAttorneyName": "Indsamling Attorney navn",
	"CollectionsAndAttorney": "Samlinger og Attorney",
	"Comment": "Comment",
	"CommentMandatoryMessage": "Comment is mandatory",
	"CommonData": "Common Data",
	"Company": "Selskab",
	"ConfigurationCode": "Configuration Code",
	"ConfirmAddTag": "Confirm Add Tag",
	"ConfirmCopy": "Confirm Copy",
	"ConfirmVoidTags": "Confirm Void Tag(s)",
	"ConfirmedDeliveryDate": "Confirmed Delivery Date",
	"Contact": "Contact",
	"ContactInfo": "Kontaktoplysninger",
	"Container": "Container",
	"ConversionFactor": "Conversion Factor",
	"Copy": "Copy",
	"CopyFromWarehouse": "Copy From Warehouse",
	"CopyToWarehouse": "Copy To Warehouse",
	"CostCenter": "Omkostningssted",
	"CostPrice": "Omkostning",
	"CountedByUser": "Counted By User",
	"CountedLocation": "Counted Location",
	"CountedQuantity": "Counted Quantity",
	"CountedUoM": "Counted Unit of Measure",
	"CountedWithZeroOnHand": "Counted with Zero On Hand",
	"CreateDistributionOrder": "Create Distribution Order",
	"CreatePurchaseOrder": "Create Purchase Order",
	"Credit": "Kredit",
	"CreditHistory": "kredit historie",
	"CreditLimit1": "Kreditgrænse 1",
	"CreditLimit2": "Kreditgrænse 2",
	"CreditLimit2/4": "Kreditmaksimum (2/4)",
	"CreditLimit3": "Kreditgrænse 3",
	"CreditLimit4": "Kreditgrænse 4",
	"CreditRef": "Credit Ref.",
	"CreditRelease": "Credit Frigivelse",
	"Currency": "Valuta",
	"Current": "Strøm",
	"CurrentAmount": "Det nuværende beløb",
	"Customer": "Kunde",
	"Customer80/20": "Customer 80/20",
	"CustomerAndPayer": "Customer and Payer",
	"CustomerGroup": "Customer Group",
	"CustomerName": "Kundenavn",
	"CustomerNo": "Kundenummer",
	"CustomerOnly": "Customer Only",
	"CustomerOrder": "Customer ordrenummer",
	"D": "D",
	"DODemand": "DO Demand",
	"DOIssueAllocated": "DO Issue Allocated",
	"DOIssueNotAllocatedWithinTimeFence": "DO Issue Not Allocated Within Time Fence",
	"Data": "data",
	"Datamatrix(2D)": "Datamatrix (2D)",
	"DefaultPayerFromCustomer": "Standard betaleren fra kunde",
	"DeliveryMethod": "Leveringsmetode",
	"DeliveryMethods": "Levering Metoder",
	"DeliveryNo": "Levering Nummer",
	"DeliveryTerm": "Levering Term",
	"DeliveryTerms": "Leveringsbetingelser",
	"DemandTimeFence": "Demand Time Fence",
	"Description": "Beskrivelse",
	"DetailView": "Detail View",
	"DeviceID": "Device ID",
	"DifferenceAmount": "Difference Amount",
	"DifferenceAmountPercentage": "Difference Cost Percentage",
	"DifferenceQuantity": "Difference Quantity",
	"DifferenceQuantityPercentage": "Difference Quantity Percentage",
	"Discount": "Rabat",
	"Discount1": "Rabat 1",
	"Discount2": "Rabat 2",
	"DiscountAmount": "Rabat Beløb",
	"DiscountGroup": "Discount Group",
	"DiscountModel": "Discount Model",
	"DiscountTerm": "Discount Term",
	"DiscountTerms": "discount Vilkår",
	"DisplayOnHand": "Display On-Hand",
	"DisplayOptions": "Indstillinger for visning",
	"Distribution": "Distribution",
	"DistributionOrder": "Distribution Order",
	"Division": "Afdeling",
	"DivisionMustBeSpecified": "Division must be specified",
	"DueDate": "Afleveringsdato",
	"E": "E",
	"EconomicOrderQuantity": "Economic Order Quantity",
	"Email": "E-mail",
	"EmailInvoices": "Email Faktura (r)",
	"EmailPODsABBR": "Email PoD(s)",
	"EnterPrise80/20": "EnterPrise 80/20",
	"EntryDate": "registreret dato",
	"ErrorMessage": "Error Message",
	"ExistInPriceList": "Exist in Price List",
	"F": "F",
	"Facility": "Facility",
	"Facility80/20": "Facility 80/20",
	"Facility80/20IsMandatory": "Facility 80/20 is mandatory",
	"FacilityData": "Facility Data",
	"FacsmileTransNo": "Fax",
	"FilteredInventoryTags": "Filtered Inventory Tags",
	"FilteredInvoices": "filtreret fakturaer",
	"FilteredLines": "Filtered Lines",
	"FinalExtendedAmount": "Final Extended Amount",
	"FinalExtendedQuantity": "Final Extended Quantity",
	"Find": "Find",
	"FindAllPriority": "Find All Priority",
	"ForecastQuantity": "Forecast Quantity",
	"ForecastQuantityWithinTimeFence": "Forecast Quantity Within Time Fence",
	"FromWarehouse": "From Warehouse",
	"G": "G",
	"GenerateBarcodeLabels": "Generate Barcode Labels",
	"GenerateMissingTagListSheet": "Generate Missing Tag List Sheet",
	"GenerateRecountSheet": "Generate Recount Sheet",
	"GenerateTagLabels": "Generate Tag Labels",
	"GlobalData": "globale data",
	"GpPercentageABBR": "GP %",
	"GrossWeight": "Gross Weight",
	"H": "H",
	"HighBalanceAmount": "Høj Balance Beløb",
	"HighBalanceAmountByDivision": "Høj Balance Beløb Af Division",
	"HighBalancePeriod": "Høj Balance Periode",
	"HighBalancePeriodByDivision": "Høj Balance periode ved Division",
	"HighestStatus": "højeste status",
	"I": "I",
	"Id": "Id",
	"InTransitDO": "In Transit DO",
	"InTransitPO": "In Transit PO",
	"InclBackLog": "Incl Backlog",
	"IncludeZeroStock": "Include Zero Stock",
	"IncomingDO": "Incoming DO",
	"IncomingDOWithinTimeFence": "Incoming DO Within Time Fence",
	"IncomingPO": "Incoming PO",
	"IncomingPOWithinTimeFence": "Incoming PO Within Time Fence",
	"Inquiry": "Inquiry",
	"Interest": "Interesse",
	"InterestRule": "Renter Rule",
	"InternalCharge": "Intern Charge",
	"InternalTransferPrice": "Internal Transfer Price",
	"InventoryAccountingMethod": "Inventory Accounting Method",
	"InventoryAccountingMethodValidationMessage": "Inventory Accounting Method {0} is not allowed",
	"InventoryCount": "Inventory Count",
	"InventoryDate": "Inventory Date",
	"InventoryReview": "Inventory Review",
	"InventoryTags": "Inventory Tags",
	"Invoice": "Faktura",
	"InvoiceAmount": "Faktura beløb",
	"InvoiceDate": "Fakturadato",
	"InvoiceDueDate": "Afleveringsdato",
	"InvoiceFilter": "Faktura Filter",
	"InvoiceNo": "fakturanummer",
	"InvoiceOrder": "Faktura Order",
	"InvoiceOverdueAmount": "forfaldne beløb",
	"InvoiceYear": "Faktura År",
	"Invoices": "Fakturaer",
	"IssueMethod": "Issue Method",
	"ItemAverageCost": "Item Average Cost",
	"ItemAverageCostIsMandatoryAndMustBeGreater0WhenInventoryAccountingMethodIs2": "Item average cost is mandatory and must be > 0 when inventory accounting method is '2'",
	"ItemAverageCostMustBeAVaildNumber": "Item average cost must be a vaild number",
	"ItemBalanceIdentityDetails": "Item Balance Identity Details",
	"ItemCost": "Item Cost",
	"ItemDescription": "Varebeskrivelse",
	"ItemDetails": "Item Details",
	"ItemGroup": "Item Group",
	"ItemGroupDescription": "Item Group Description",
	"ItemMaintenance": "Item Maintenance",
	"ItemNo": "Varenummer",
	"ItemNumberMandatoryMessage": "Item Number is mandatory",
	"ItemType": "Item Type",
	"ItemTypeDescription": "Item Type Description",
	"ItemsToPlan": "Items To Plan",
	"J": "J",
	"JobName": "Job Name",
	"JobNumber": "Job Number",
	"JournalNo": "Journal nummer",
	"JournalSequenceNo": "Journal Sequence Number",
	"K": "K",
	"KeyData": "Key Data",
	"L": "L",
	"LabelPrinting": "Label Printing",
	"LabelSize": "Label Size",
	"Language": "Sprog",
	"Languages": "Languages",
	"Last30Days": "Last 30 Days",
	"LastInvoiceDate": "Sidste Faktura Dato",
	"LastNETPaymentAmount": "Sidste NET Betaling Beløb",
	"LastNETPaymentDate": "Sidste NET Betalingsdato",
	"LastPayment": "sidste betaling",
	"LastPaymentAmount": "Sidste betaling Beløb",
	"LastPaymentDate": "Sidste Betalingsdato",
	"LeadTimeDO": "Lead Time DO",
	"LeadTimePO": "Lead Time PO",
	"LineAmount": "Linje Beløb",
	"LineCharges": "linje Afgifter",
	"LineSuffix": "nummersuffiks",
	"LocalData": "lokale data",
	"Location": "Beliggenhed",
	"LoctionMandatoryMessage": "Location is mandatory",
	"LotControlMethod": "Lot Control Method",
	"LotNo": "Lot nummer",
	"LotReference": "Lot Reference",
	"LowestStatus": "Laveste status",
	"Lrec": "Last Receipt Date",
	"LrecABBR": "Lrec",
	"M": "M",
	"MandatoryData": "Mandatory Data",
	"ManualDueDate": "Manuel Forfaldsdato",
	"ManufacturedQuantity": "Manufactured Quantity",
	"MasterData": "Master Data",
	"MaterialPlan": "Material Plan",
	"MaxStock": "Max Stock",
	"MaximumQuantity": "Maximum Quantity",
	"Menu": "Menu",
	"MerchandiseArea": "Merchandise Area",
	"MessageNumber": "Message Number",
	"MessageType": "Message Type",
	"MessageWasRelayedtoMailServerSuccessFullyAndQueuedForMailing": "Message was relayed to mail server successfully and queued for mailing.",
	"MinimumQuantity": "Minimum Quantity",
	"Miscellaneous": "Miscellaneous",
	"MissingItems": "Missing Items",
	"MissingTags": "Missing Tags",
	"Months": "Months",
	"MonthsOnhandAvailable": "Months Onhand - Available",
	"MonthsOnhandStock": "Months Onhand - Stock",
	"N": "N",
	"NegativePhysicalVariance": "Negative Physical Variance",
	"NegativeTransfer": "Negative Transfer",
	"Net": "Netto",
	"NetAmount": "Netto beløb",
	"NetOrderValue": "Netto beløb",
	"NetPrice": "Netto pris",
	"NetWeight": "Net Weight",
	"NewOnHandBalance": "New On Hand Balance",
	"NewOnHandBalancePerTransactionDate": "New On Hand Balance Per Transaction Date",
	"Next": "Next",
	"No": "Ingen",
	"NoFilter": "No filter",
	"NoOfDaysOverdue": "Antal dage Forfaldne",
	"Notes": "Noter",
	"NumberOfDaysPastDue": "Ikke betalt til tiden",
	"O": "O",
	"OK": "Okay",
	"OfficialTranslations": "Official Translations",
	"OnHand": "On-Hand",
	"OnHandAmount": "On-Hand Amount",
	"OnHandApproveQuantity": "On-Hand Approve Quantity",
	"OnHandBalance": "On-Hand Balance",
	"OnHandBalances": "On-Hand Balances",
	"OnHandInspectQuantity": "On-Hand Inspect Quantity",
	"OnHandNonRejectInspectQuantity": "On-Hand Non-Reject/Inspect Quantity",
	"OnHandQuantity": "On-Hand Quantity",
	"OnHandRejectQuantity": "On-Hand Reject Quantity",
	"OnOrderQuantity": "On-Order Quantity",
	"OnOrderQuantitySupply": "On-Order Quantity (Supply)",
	"OpenCOABBR": "Open CO",
	"OpenDOABBR": "Open DO",
	"OpenDistributionOrders": "Open Distribution Orders",
	"OpenInvoices": "Open Invoices",
	"OpenMOABBR": "Open MO",
	"OpenOrders": "Open Orders",
	"OpenPOABBR": "Open PO",
	"OpenPlatformOrders": "Open Platform Orders",
	"OpenPurchaseOrders": "Open Purchase Orders",
	"OpenSalesOrders": "Open Sales Orders",
	"OpenStockOrders": "Open Stock Orders",
	"OpenedDate": "åbnede Dato",
	"OrderCategory": "Order Category",
	"OrderDate": "Bestillingsdato",
	"OrderLine": "Order Line",
	"OrderLineNo": "Linje nummer",
	"OrderLines": "Bestil Lines",
	"OrderMultiple": "Order Multiple",
	"OrderMultipleIsMandatoryAndMustBeGreaterThan0WhenAcquisitonCodeIs2": "Order Multiple is mandatory and must be > 0 when acquisition code is '2'",
	"OrderNo": "Ordrenummer",
	"OrderTransactions": "Bestil Transaktioner",
	"OrderType": "Bestil Type",
	"OrderTypeValidationMessageForAcquisitionCode2": "Order Type {0} is not allowed when acquisition code is '2'",
	"OrderTypeValidationMessageForAcquisitionCode3": "Order Type {0} is not allowed when acquisiton code is '3' {1}",
	"OrderTypeValidationMessageForWarehousePAcquisitionCode1": "Order Type {0} is not allowed when copy to warehouse type is 'P'  and acquisition code is '1'",
	"OrderTypeValidationMessageForWarehousePAcquisitionCode2": "Order Type {0} is not allowed when copy to warehouse type is 'P' and acquisition code is '2'",
	"OrderTypeValidationMessageForWarehouseSAcquisitionCode2": "Order Type {0} is not allowed when copy to warehouse type is 'S' and acquisition code is '2'",
	"OrderTypes": "Bestil typer",
	"Orders": "ordrer",
	"OurReference": "Job Name",
	"OutstandingBalance": "Udestående saldo",
	"OutstandingBalanceByDivision": "Udestående saldo Af Division",
	"OutstandingDemand": "Outstanding Demand",
	"OutstandingSupply": "Outstanding Supply",
	"OverAmount": "Over Amount",
	"OverBenchmark": "Over Benchmark",
	"OverQuantity": "Over Quantity",
	"OverSoldQuantity": "Over Sold Quantity",
	"OverdueAmount": "forfaldne beløb",
	"P": "P",
	"PackageNumber": "Package Number",
	"PackagingInfo": "Packaging Info",
	"PaidAmount": "Betalt beløb",
	"PaidInvoices": "Paid Invoices",
	"PalletPer20FT": "Pallet Per 20FT",
	"PalletPer40FT": "Pallet Per 40FT",
	"Partner": "Partner",
	"PartnerID": "Partner ID",
	"Payer": "Payer",
	"PayerName": "Payer Navn",
	"PayerNo": "Payer Number",
	"PayerOnly": "Payer Only",
	"PaymentDate": "Betalingsdato",
	"PaymentDetails": "Betalingsoplysninger",
	"PaymentDocumentNumber": "Betaling Document Number",
	"PaymentMethod": "Betalingsmetode",
	"PaymentNo": "Betaling Antal",
	"PaymentTerm": "Betalingsbetingelser",
	"PaymentTerms": "Betalingsbetingelser",
	"Payments": "Betalinger",
	"PendingDiscount": "Pending Discount",
	"Period": "Period",
	"PeriodBalances": "Period Balances",
	"PeriodEndingBalanceQuantity": "Period Ending Balance Quantity",
	"PeriodStartingBalanceQuantity": "Period Starting Balance Quantity",
	"Phone": "Telefon",
	"PhysicalInventoryLine": "Physical Inventory Line",
	"PickListSuffix": "Pick List Suffix",
	"Planning": "Planning",
	"PlanningData": "Planning Data",
	"PlanningDate": "Planning Date",
	"PlanningDetails": "Planning Details",
	"PlanningTimeFence": "Planning Time Fence",
	"Platform": "Platform",
	"PlatformItem": "Platform Item",
	"PlatformPOQuantity": "Platform PO Quantity",
	"PleaseEnterAVaildSearchInput": "Please enter a vaild search input",
	"PleaseEnterAtleastOneSearchInput": "Please enter atleast one search input",
	"PleaseProvideAValidItemNumber": "Please provide a valid Item number",
	"PleaseSelectACustomer": "Please select a customer",
	"PleaseSelectACustomer/Payer": "Please select a Customer and/or Payer",
	"PleaseSelectALine": "Please select a line",
	"PleaseSelectAPayer": "Please select a payer",
	"PleaseSelectAPayerOrCheckNumber": "Please select a payer or specify Check number",
	"PleaseSelectATicklerNoteToEdit": "Please select a tickler note to edit",
	"PleaseSelectAWarehouseFromTheDropdownToCopyTo": "Plese select a warehouse from the drop down to copy to",
	"PleaseSelectAWarehouseFromTheListToCopyFrom": "Please select a warehouse from the list to copy from",
	"PleaseSelectAnInventoryCount": "Please select an inventory count",
	"PleaseSelectAtleastOneInvoice": "Please select atleast one invoice",
	"PleaseSelectAtleastOneLine": "Please select atleast one line",
	"PleaseSelectAtleastOneOrderToRelease": "Please select atleast one order to release",
	"PleaseSelectLinesToLoadTheDocumentsFromIDM": "Vælg fakturaen at indlæse dokumenter fra IDM",
	"PleaseSelectOnly1Line": "Please select only 1 line",
	"PositivePhysicalVariance": "Positive Physical Variance",
	"PositiveTransfer": "Positive Transfer",
	"PreLien": "Pre-Lien",
	"PriceList": "Prisliste",
	"PriceOrigin": "pris Origin",
	"Pricing": "Priser",
	"Priority": "Priority",
	"ProductGroup": "Product Group",
	"ProductGroupDescription": "Product Group Description",
	"ProductLine": "Product Line",
	"ProductionLine": "Production Line",
	"ProductionLineIsMandatoryWhenAcquisitionCodeIs1": "Production line is mandatory when acquisition code is '1'",
	"ProductionLineShouldBeBlankWhenAcquisitionCodeIs2": "Production line should be blank when acquisition code is '2'",
	"ProductionLineShouldBeBlankWhenAcquisitionCodeIs3": "Production line should be blank when acquisition code is '3'",
	"Project": "Project",
	"Project2": "Job Number",
	"ProjectHoldQuantity": "Project Hold Quantity",
	"ProjectedOnhandQuantity": "Projected Onhand Quantity",
	"ProofOfDelivery": "Bevis for levering",
	"ProofOfDeliveryABBR": "PoD",
	"ProposedQuantity": "Proposed Quantity",
	"ProposedQuantityDO": "Proposed Quantity DO",
	"ProposedQuantityPO": "Proposed Quantity PO",
	"Purchase": "Purchase",
	"PurchaseOrder": "Purchase Order",
	"PurchaseOrderNo": "Købsordrenummer",
	"PurchaseOrderNoABBR": "PO No",
	"PurchaseOrderUnitOfMeasure": "Purchase Order Unit Of Measure",
	"PurchasePrice": "Purchase Price",
	"PurchasePriceUnitOfMeasure": "Purchase Price Unit Of Measure",
	"PurchasedQuantity": "Purchased Quantity",
	"Q": "Q",
	"Quantity": "Mængde",
	"R": "R",
	"ReasonCode": "Reason Code",
	"Recipient": "Modtager",
	"RecordedAmount": "Faktura beløb",
	"RecountPrinted": "Recount Printed",
	"Reference": "Reference",
	"ReferenceNo": "Referencenummer",
	"ReferenceOrderCategory": "Reference Order Category",
	"ReferenceOrderLine": "Reference Order Line",
	"ReferenceOrderNumber": "Reference Order Number",
	"ReferenceText": "Reference Text",
	"RegistrationDate": "registreret dato",
	"RegistrationTime": "Registered Time",
	"Reload": "Opdater",
	"Remaining": "Resterende",
	"RemainingAmount": "resterende beløb",
	"RemainingManufacturerQuantityABBR": "Remaining Mfg Qty",
	"RemainingQuantity": "Remaining Quantity",
	"Remark": "Remark",
	"Remove": "Remove",
	"ReorderPoint": "Reorder Point",
	"RequestedDeliveryDate": "Anmodet leveringsdato",
	"ReservedQuantity": "Reserved Quantity",
	"ReservedQuantityDemand": "Reserved Quantity (Demand)",
	"Responsible": "Ansvarlig",
	"Results": "Resultater",
	"Rolling": "Rolling",
	"S": "S",
	"SafetyStock": "Safety Stock",
	"SafetyStockMin": "Safety Stock (Min)",
	"SafetyStockQuantity": "Safety Stock Quantity",
	"Sales": "Salg",
	"SalesCampaign": "Kampagne",
	"SalesPerson": "Sælger",
	"SalesPersonCode": "Sælger",
	"SalesPersonName": "Navn",
	"SalesPrice": "Salg Pris",
	"SalesPriceQuantity": "Salg Pris Mængde",
	"SalesPriceUnitOfMeasure": "Salg Pris Unit",
	"Save": "Spare",
	"SaveAll": "Gem alle",
	"Search": "Søge",
	"SelectCustomer": "Vælg kunde",
	"SelectDateRange": "Vælg datointerval",
	"SelectDivision": "Vælg Division",
	"SelectPayer": "Vælg Payer",
	"SelectedInventoryTags": "Selected Inventory Tags",
	"SelectedInvoices": "Valgte fakturaer",
	"SelectedItems": "Selected Items",
	"Selection": "Udvælgelse",
	"SelectionView": "Selection View",
	"SendEmail": "Send Email",
	"SentToCollectionsDate": "Sendt til Samlinger Dato",
	"ShortAmount": "Short Amount",
	"ShortQuantity": "Short Quantity",
	"ShowCashDesk": "Vis Cash Desk",
	"ShowIDM": "Vis IDM",
	"SoldQuantity": "Sold Quantity",
	"StandardCost": "Standard Cost",
	"Statement": "Erklæring",
	"StatementRule": "erklæring Rule",
	"Status": "Status",
	"Stock": "Stock",
	"StockManufacturedQuantity": "Stock Manufactured Quantity",
	"StockPOQuantity": "Stock PO Quantity",
	"StockZone": "Stock Zone",
	"Stop": "Stop",
	"SubjectIsMandatory": "Subject is mandatory",
	"SuccessfullyCopiedMessage": "Successfully copied Item {0} from warehouse {1}, to warehouse {2}",
	"Summary": "Summary",
	"Supplier": "Supplier",
	"SupplierIsMandatoryWhenAcquisitonCodeIs2": "Supplier is mandatory when acquisition code is '2'",
	"SupplierManufacturerDate": "Supplier Manufacturer Date",
	"SupplierManufacturerQuantity": "Supplier Manufacturer Quantity",
	"SupplierName": "Supplier Name",
	"SupplierShouldBeBlankWhenAcquisitionCodeIs1": "Supplier should be blank when acquisition code is '1'",
	"SupplierShouldBeBlankWhenAcquisitionCodeIs3": "Supplier should be blank when acquisition code is '3'",
	"SupplyChainPlanning": "Supply Chain Planning",
	"SupplyingWarehouse": "Supplying Warehouse",
	"SupplyingWarehouseShouldBeBlankWhenAcquistionCodeIs1": "Supplying warehouse should be blank when acquisition code is '1'",
	"SupplyingWarehouseShouldBeBlankWhenAcquistionCodeIs2": "Supplying warehouse should be blank when acquisition code is '2'",
	"T": "T",
	"TagLabels": "Tag Labels",
	"TagListing": "Tag Listing",
	"TagNumber": "Tag Number",
	"TagNumberRange": "Tag Number Range",
	"TagVariance": "Tag Variance",
	"TargetInventory": "Target Inventory",
	"Tax": "Skat",
	"TaxAmount": "Skat Beløb",
	"TaxCodeCustABBR": "Tax Cust/Adr",
	"TelePhoneNo1": "Telefon",
	"TelePhoneNo2": "Telefon 1",
	"TheCopyFromAndToWarehousesCannotBeSamePleaseCheckYourSelection": "The copy from and to warehouses cannot be same, please check your selection",
	"Theme1Name": "LeanSwift Chartreuse",
	"Theme2Name": "Royal Infor",
	"Theme3Name": "Summer Smoothie",
	"Theme4Name": "Pumkin Spice",
	"Theme5Name": "Vision Impaired",
	"Theme6Name": "Lipstick Jungle",
	"Theme7Name": "Silver Lining",
	"Theme8Name": "Steel Clouds",
	"Themes": "Themes",
	"TicklerNote": "Tickler Note",
	"TicklerNotes": "Tickler Notes",
	"ToWarehouse": "To Warehouse",
	"Total Variance": "Total Variance",
	"TotalInTransit": "Total InTransit",
	"TotalInventoryTags": "Total Inventory Tags",
	"TotalInvoices": "Total fakturaer",
	"TotalItems": "Total Items",
	"TotalLines": "Total Lines",
	"TotalNegativeVariance": "Total Negative Variance",
	"TotalOnHandBalance": "Total On Hand Balance",
	"TotalOrderValueNet": "Faktura alt",
	"TotalPositiveVariance": "Total Positive Variance",
	"TotalSales": "GP Sales",
	"TotalUsage": "Total Usage",
	"Totals": "totaler",
	"TransacionQuantity": "Transaction Quantity",
	"TransactionAmount": "TransactionAmount",
	"TransactionDate": "Transaction Date",
	"TransactionIdABBR": "Transaction Id",
	"TransactionTime": "Transaction Time",
	"TransactionType": "Transaction Type",
	"Transfer": "Transfer",
	"TransferCount": "Transfer Count",
	"TransferErrors": "Transfer Errors",
	"Type": "Type",
	"U": "U",
	"UnAllocatedQuantity": "Un Allocated Quantity",
	"UnderBenchmark": "Under Benchmark",
	"Unit": "Enhed",
	"UnitOfMeasure": "Unit of Measure",
	"UpdateTagQuantities": "Update Tag Quantities",
	"UploadedByUser": "Uploaded By User",
	"UsedQuantity": "Used Quantity",
	"User": "Bruger",
	"UserDefined": "Brugerdefineret",
	"UserDefinedCustomField": "User Defined Custom Field",
	"V": "V",
	"ValidEmailAddressWarningMessage": "Enter a valid email address",
	"ValidFrom": "Valid From",
	"ValidTags": "Valid Tags",
	"ValidTo": "Valid To",
	"VatAmount": "Skat Beløb",
	"Version": "Version",
	"VoidFollowingTagsText": "You are about to Void the following Tag(s)",
	"VoidTags": "Void Tag(s)",
	"VoidedTags": "Voided Tags",
	"VoucherNo": "bilagsnummer",
	"VoucherText": "Voucher tekst",
	"W": "W",
	"Wallpaper1Name": "Diamond",
	"Wallpaper2Name": "Grid",
	"Wallpaper3Name": "Linen",
	"Wallpaper4Name": "Tiles",
	"Wallpaper5Name": "Wood",
	"Wallpapers": "Wallpapers",
	"Warehouse": "Lager",
	"WarehouseData": "Warehouse Data",
	"WarehouseGroup": "Warehouse Group",
	"WarehouseName": "Warehouse Name",
	"WarehouseStatistics": "Warehouse Statistics",
	"WarehouseStockTransactions": "Warehouse Stock Transactions",
	"X": "X",
	"Y": "Y",
	"Year": "År",
	"Years": "Years",
	"Yes": "Ja",
	"YourRef1": "Kontakt",
	"YourRef2": "DBA",
	"Z": "Z",
	"ZeroCounted": "Zero Counted",
	"ar-AR": "Arabic",
	"cs-CZ": "Czech (Czech Republic)",
	"da-DK": "Dansk (Danmark)",
	"de-DE": "German (Germany)",
	"el-GR": "Greek (Greece)",
	"en-GB": "English (United Kingdom)",
	"en-US": "English (United States)",
	"es-ES": "Spanish",
	"fi-FI": "Finnish (Finland)",
	"fr-FR": "French (France)",
	"he-IL": "Hebrew (Israel)",
	"hu-HU": "Hungarian (Hungary)",
	"it-IT": "Italian (Italy)",
	"ja-JP": "Japanese (Japan)",
	"nb-NO": "Norwegian (Bokmål)",
	"nl-NL": "Dutch (Netherlands)",
	"pl-PL": "Polish (Poland)",
	"pt-BR": "Portuguese (Brazil)",
	"pt-PT": "Portuguese (Portugal)",
	"ru-RU": "Russian (Russia)",
	"sv-SE": "Swedish (Sweden)",
	"ta-IN": "Tamil (India)",
	"tr-TR": "Turkish (Turkey)",
	"zh-CN": "Chinese (Simplified)"
}